{"digest":"b4ea2f383a74e03627537c7388320d90b9fb02f7","css":"atom-text-editor,\n:host {\n  background-color: #282828;\n  color: #f8f8f2;\n}\natom-text-editor .wrap-guide,\n:host .wrap-guide {\n  background-color: rgba(255, 255, 255, 0.1);\n}\natom-text-editor .indent-guide,\n:host .indent-guide {\n  color: rgba(255, 255, 255, 0.15);\n}\natom-text-editor .invisible-character,\n:host .invisible-character {\n  color: rgba(197, 200, 198, 0.2);\n}\natom-text-editor .gutter,\n:host .gutter {\n  background-color: #303030;\n  color: #f8f8f2;\n}\natom-text-editor .gutter .line-number.cursor-line,\n:host .gutter .line-number.cursor-line {\n  background-color: #49483e;\n  color: #f8f8f2;\n}\natom-text-editor .gutter .line-number.cursor-line-no-selection,\n:host .gutter .line-number.cursor-line-no-selection {\n  color: #f8f8f2;\n}\natom-text-editor .gutter .line-number.folded,\n:host .gutter .line-number.folded,\natom-text-editor .gutter .line-number:after,\n:host .gutter .line-number:after,\natom-text-editor .fold-marker:after,\n:host .fold-marker:after {\n  color: #cccccc;\n}\natom-text-editor .invisible,\n:host .invisible {\n  color: #f8f8f2;\n}\natom-text-editor .cursor,\n:host .cursor {\n  color: #f8f8f0;\n}\natom-text-editor .selection .region,\n:host .selection .region {\n  background-color: #49483e;\n}\natom-text-editor .search-results .marker .region,\n:host .search-results .marker .region {\n  background-color: transparent;\n  border: 1px solid #888888;\n}\natom-text-editor .search-results .marker.current-result .region,\n:host .search-results .marker.current-result .region {\n  border: 1px solid #ffffff;\n}\n.comment {\n  color: #75715e;\n}\n.entity.name.type {\n  color: #ffd569;\n}\n.entity.other.inherited-class {\n  font-style: italic;\n  text-decoration: none;\n  color: #a6e22e;\n}\n.entity.name.function {\n  color: #a6e22e;\n}\n.entity.name.class,\n.entity.name.type.class {\n  text-decoration: none;\n  color: #a6e22e;\n}\n.entity.name.instance {\n  color: #66d9ef;\n}\n.entity.name.tag {\n  color: #f92672;\n}\n.entity.other.attribute-name {\n  color: #a6e22e;\n}\n.entity.other.attribute-name.parent-selector {\n  color: #ffd569;\n}\n.invalid {\n  color: #f8f8f0;\n  background-color: #f92672;\n}\n.invalid.deprecated {\n  background-color: #ae81ff;\n}\n.keyword {\n  color: #f92672 !important;\n}\n.storage {\n  color: #f92672;\n}\n.storage.type {\n  font-style: italic;\n  color: #66d9ef;\n}\n.constant.character.escape,\n.constant.numeric,\n.constant.other.color,\n.constant.other.rgb-value,\n.constant.other.symbol {\n  color: #ae81ff;\n}\n.variable {\n  color: #fd971f;\n}\n.variable.parameter {\n  font-style: italic;\n}\n.variable.language.python,\n.variable.language.js {\n  color: #f92672;\n}\n.string {\n  color: #e6db74;\n}\n.punctuation.definition.comment {\n  color: #75715e;\n}\n.punctuation.definition.string {\n  color: #e6db74;\n}\n.punctuation.definition.parameters {\n  color: #f92672;\n}\n.punctuation.definition.variable,\n.punctuation.definition.array {\n  color: #f8f8f2;\n}\n.punctuation.definition.heading,\n.punctuation.definition.identity {\n  color: #66d9ef;\n}\n.punctuation.definition.bold {\n  color: #ffd569;\n  font-weight: bold;\n}\n.punctuation.definition.italic {\n  color: #ae81ff;\n  font-style: italic;\n}\n.punctuation.section {\n  color: #66d9ef;\n}\n.punctuation.section.embedded {\n  color: #e60657;\n}\n.punctuation.terminator {\n  color: #f92672;\n}\n.support.class,\n.support.type {\n  color: #66d9ef;\n}\n.support.constant,\n.support.variable,\n.support.function {\n  font-style: italic;\n  color: #66d9ef;\n}\n.meta.class {\n  color: #ffd569;\n}\n.meta.link {\n  color: #fd971f;\n}\n.meta.require {\n  color: #66d9ef;\n}\n.meta.selector {\n  color: #ae81ff;\n}\n.meta.separator {\n  background-color: #888888;\n  color: #f8f8f2;\n}\n.meta.brace {\n  color: #66d9ef;\n}\n.meta.brace.round {\n  color: #f92672;\n}\n.meta.delimiter {\n  color: #fd971f;\n}\n.meta.structure.value > .string,\n.meta.structure.value > .string > .punctuation,\n.meta.structure.value > .constant {\n  color: #ae81ff;\n}\n.meta.structure > .punctuation.definition .dictionary,\n.meta.structure > .punctuation.definition .array {\n  color: #66d9ef;\n}\n.meta.structure > .punctuation.separator {\n  color: #f92672;\n}\n.none {\n  color: #f8f8f2;\n}\n.markup.bold {\n  color: #fd971f;\n  font-weight: bold;\n}\n.markup.changed {\n  color: #ae81ff;\n}\n.markup.deleted {\n  color: #f92672;\n}\n.markup.italic {\n  color: #ae81ff;\n  font-style: italic;\n}\n.markup.heading .punctuation.definition.heading {\n  color: #66d9ef;\n}\n.markup.inserted {\n  color: #a6e22e;\n}\n.markup.list {\n  color: #f92672;\n}\n.markup.quote {\n  color: #fd971f;\n}\n.markup.raw.inline {\n  color: #a6e22e;\n}\n.source.gfm .markup {\n  -webkit-font-smoothing: auto;\n}\n.source.gfm .markup.heading {\n  color: #a6e22e;\n  font-weight: bold;\n}\n.source.gfm .markup.underline {\n  color: #e6db74;\n  text-decoration: underline;\n}\n.source.gfm .bold {\n  font-weight: bold;\n}\n.source.gfm .italic {\n  font-style: italic;\n}\n.source.gfm .raw {\n  color: #66d9ef;\n}\n.source.gfm .variable.list {\n  color: #f92672;\n  font-weight: bold;\n}\n.source.gfm .link {\n  color: #cccccc;\n}\n.source.gfm .link .entity {\n  color: #ae81ff;\n}\natom-text-editor[mini] .scroll-view,\n:host([mini]) .scroll-view {\n  padding-left: 1px;\n}\n.leading-whitespace,\n.trailing-whitespace {\n  display: inline-block;\n}\n","imports":[{"path":"static/variables/ui-variables.less","digest":"8941827f61ffe6109d099580717e5ea2d0b9cd3c"},{"path":"static/variables/syntax-variables.less","digest":"812c1b7883a023f768773d14294653adcdb932d7"},{"path":"/cath/homes2/zcapamu/.atom/packages/monokai-verbose-syntax/styles/base.less","digest":"88913236c5fd83981b303825a3374865fee4b47b"},{"path":"/cath/homes2/zcapamu/.atom/packages/monokai-verbose-syntax/styles/syntax-variables.less","digest":"4d57bb2475ae36e1285b75cd2571b469e0cb45b8"},{"path":"/cath/homes2/zcapamu/.atom/packages/monokai-verbose-syntax/styles/colors.less","digest":"8cf1c680a15e9f2513b22ef49027965ab21842c1"}],"version":1}